azure/agrifood/farming/__init__.py
azure/agrifood/farming/_client.py
azure/agrifood/farming/_configuration.py
azure/agrifood/farming/_patch.py
azure/agrifood/farming/_serialization.py
azure/agrifood/farming/_vendor.py
azure/agrifood/farming/_version.py
azure/agrifood/farming/py.typed
azure/agrifood/farming/aio/__init__.py
azure/agrifood/farming/aio/_client.py
azure/agrifood/farming/aio/_configuration.py
azure/agrifood/farming/aio/_patch.py
azure/agrifood/farming/aio/_vendor.py
azure/agrifood/farming/aio/operations/__init__.py
azure/agrifood/farming/aio/operations/_operations.py
azure/agrifood/farming/aio/operations/_patch.py
azure/agrifood/farming/operations/__init__.py
azure/agrifood/farming/operations/_operations.py
azure/agrifood/farming/operations/_patch.py
azure_agrifood_farming-1.0.0b2.dist-info/LICENSE
azure_agrifood_farming-1.0.0b2.dist-info/METADATA
azure_agrifood_farming-1.0.0b2.dist-info/WHEEL
azure_agrifood_farming-1.0.0b2.dist-info/top_level.txt
azure_agrifood_farming-1.0.0b2.dist-info/RECORD
